bpp_af/__init__.py
bpp_af/af.py
bpp_af/extract.py
bpp_af/instance.py
bpp_af-0.0.1.dist-info/METADATA
bpp_af-0.0.1.dist-info/WHEEL
bpp_af-0.0.1.dist-info/RECORD
